maze_nd/__init__.py
maze_nd/colors.py
maze_nd/draw.py
maze_nd/maze_nd.py
maze_nd-0.1.1.dist-info/LICENSE
maze_nd-0.1.1.dist-info/METADATA
maze_nd-0.1.1.dist-info/WHEEL
maze_nd-0.1.1.dist-info/RECORD
