Metadata-Version: 2.1
Name: maze-nd
Version: 0.1.1
Summary: A python package for generating and visualizing n-dimensional mazes.
License: MIT
Author: Daniel
Author-email: huffdanielt@gmail.com
Requires-Python: >=3.10,<4.0
Classifier: License :: OSI Approved :: MIT License
Classifier: Programming Language :: Python :: 3
Classifier: Programming Language :: Python :: 3.10
Classifier: Programming Language :: Python :: 3.11
Classifier: Programming Language :: Python :: 3.12
Requires-Dist: numpy (>=1.26.2,<2.0.0)
Requires-Dist: opencv-python (>=4.8.1.78,<5.0.0.0)
Requires-Dist: pillow (>=10.1.0,<11.0.0)
